sbc_drf/__init__.py
sbc_drf/apps.py
sbc_drf/dispatch.py
sbc_drf/errors.py
sbc_drf/filters.py
sbc_drf/handlers.py
sbc_drf/middleware.py
sbc_drf/pagination.py
sbc_drf/permissions.py
sbc_drf/renderer.py
sbc_drf/routers.py
sbc_drf/tests.py
sbc_drf/views.py
sbc_drf/mixins/__init__.py
sbc_drf/mixins/db.py
sbc_drf/mixins/serializer.py
sbc_drf/mixins/viewset.py
sbc_drf-1.1.7.dist-info/LICENSE
sbc_drf-1.1.7.dist-info/METADATA
sbc_drf-1.1.7.dist-info/WHEEL
sbc_drf-1.1.7.dist-info/top_level.txt
sbc_drf-1.1.7.dist-info/zip-safe
sbc_drf-1.1.7.dist-info/RECORD
