Metadata-Version: 2.1
Name: sbc-drf
Version: 1.1.7
Summary: A few extensions to DRF.
Home-page: https://gitlab.stickboycreative.com/sbc-python/sbc_drf
Author: Abhinav Kotak
Author-email: in.abhi9@gmail.com
Maintainer: Abhinav Kotak
Maintainer-email: in.abhi9@gmail.com
License: MIT License
Requires-Dist: six
Requires-Dist: wheel
Requires-Dist: drf-extensions (<0.8,>=0.6.0)
Requires-Dist: djangorestframework (<4.0,>=3.11)
Requires-Dist: Django (<=3.2.0,>=3.0)
Requires-Dist: raven (<8,>=6)
